odoo/addons/delivery_free_fee_removal/README.rst
odoo/addons/delivery_free_fee_removal/__init__.py
odoo/addons/delivery_free_fee_removal/__manifest__.py
odoo/addons/delivery_free_fee_removal/i18n/delivery_free_fee_removal.pot
odoo/addons/delivery_free_fee_removal/i18n/es.po
odoo/addons/delivery_free_fee_removal/models/__init__.py
odoo/addons/delivery_free_fee_removal/models/sale_order.py
odoo/addons/delivery_free_fee_removal/readme/CONTRIBUTORS.rst
odoo/addons/delivery_free_fee_removal/readme/DESCRIPTION.rst
odoo/addons/delivery_free_fee_removal/static/description/icon.png
odoo/addons/delivery_free_fee_removal/static/description/index.html
odoo/addons/delivery_free_fee_removal/tests/__init__.py
odoo/addons/delivery_free_fee_removal/tests/test_delivery_free_fee_removal.py
odoo11_addon_delivery_free_fee_removal-11.0.1.0.0.99.dev7.dist-info/METADATA
odoo11_addon_delivery_free_fee_removal-11.0.1.0.0.99.dev7.dist-info/WHEEL
odoo11_addon_delivery_free_fee_removal-11.0.1.0.0.99.dev7.dist-info/top_level.txt
odoo11_addon_delivery_free_fee_removal-11.0.1.0.0.99.dev7.dist-info/RECORD
